<?xml version="1.0" encoding="UTF-8"?>
<dungeons>
	<dungeon id="0">
		<floorSizeX>3</floorSizeX>
		<floorSizeY>4</floorSizeY>
		<minRoomSize>4</minRoomSize>
		<maxRoomSize>6</maxRoomSize>
		<enemy EnemyID="0" frequency="10">太郎</enemy>
		<enemy EnemyID="2" frequency="10">２郎</enemy>
		<enemy EnemyID="3" frequency="10">４郎</enemy>
		<item ItemID="1" frequency="10">短剣</item>
		<item ItemID="2" frequency="5">短剣</item>
		<item ItemID="11" frequency="5">斧</item>
		<item ItemID="41" frequency="5">爆弾</item>
		<item ItemID="52" frequency="5">パン</item>
		<item ItemID="61" frequency="10">花束</item>
	</dungeon>
	<dungeon id="1">
		<floorSizeX>2</floorSizeX>
		<floorSizeY>3</floorSizeY>
		<minRoomSize>6</minRoomSize>
		<maxRoomSize>9</maxRoomSize>
		<enemy EnemyID="0" frequency="10">太郎</enemy>
		<enemy EnemyID="3" frequency="10">４郎</enemy>
	</dungeon>
</dungeons>